navalmartin_mir_vision_utils/__init__.py
navalmartin_mir_vision_utils/exceptions.py
navalmartin_mir_vision_utils/image_enums.py
navalmartin_mir_vision_utils/image_loaders.py
navalmartin_mir_vision_utils/image_transformers.py
navalmartin_mir_vision_utils/image_utils.py
navalmartin_mir_vision_utils/mir_vision_config.py
navalmartin_mir_vision_utils/mir_vision_types.py
navalmartin_mir_vision_utils/plot_images.py
navalmartin_mir_vision_utils/.idea/.gitignore
navalmartin_mir_vision_utils/.idea/misc.xml
navalmartin_mir_vision_utils/.idea/modules.xml
navalmartin_mir_vision_utils/.idea/navalmartin_mir_vision_utils.iml
navalmartin_mir_vision_utils/.idea/vcs.xml
navalmartin_mir_vision_utils/.idea/workspace.xml
navalmartin_mir_vision_utils/.idea/inspectionProfiles/Project_Default.xml
navalmartin_mir_vision_utils/.idea/inspectionProfiles/profiles_settings.xml
navalmartin_mir_vision_utils/examples/__init__.py
navalmartin_mir_vision_utils/examples/compute_image_quality.py
navalmartin_mir_vision_utils/examples/compute_image_statistics.py
navalmartin_mir_vision_utils/examples/eda_images.py
navalmartin_mir_vision_utils/examples/image_augmentation_generation.py
navalmartin_mir_vision_utils/examples/image_transformations_examples.py
navalmartin_mir_vision_utils/examples/image_utils_examples.py
navalmartin_mir_vision_utils/examples/image_utils_with_aws.py
navalmartin_mir_vision_utils/examples/load_labeled_dataset.py
navalmartin_mir_vision_utils/image_quality/__init__.py
navalmartin_mir_vision_utils/image_quality/brisque.py
navalmartin_mir_vision_utils/image_quality/models/__init__.py
navalmartin_mir_vision_utils/image_quality/models/brisque_svm.txt
navalmartin_mir_vision_utils/image_quality/models/normalize.pickle
navalmartin_mir_vision_utils/mir_vision_io/__init__.py
navalmartin_mir_vision_utils/mir_vision_io/file_utils.py
navalmartin_mir_vision_utils/mir_vision_io/labeled_image_dataset.py
navalmartin_mir_vision_utils/mir_vision_io/tempfile.py
navalmartin_mir_vision_utils-0.0.48.dist-info/METADATA
navalmartin_mir_vision_utils-0.0.48.dist-info/WHEEL
navalmartin_mir_vision_utils-0.0.48.dist-info/licenses/LICENSE
navalmartin_mir_vision_utils-0.0.48.dist-info/RECORD
